LICENSE
README.md
pyproject.toml
slackevent_responder/__init__.py
slackevent_responder/application.py
slackevent_responder/version.py
slackevent_responder-0.1.0.dist-info/LICENSE
slackevent_responder-0.1.0.dist-info/WHEEL
slackevent_responder-0.1.0.dist-info/METADATA
slackevent_responder-0.1.0.dist-info/RECORD
