Metadata-Version: 2.1
Name: slackevent-responder
Version: 0.1.0
Summary: ASGI adapter for Slack Events API
Home-page: https://github.com/haeena/slackevent-responder
License: MIT
Author: Toshiaki Hatano
Author-email: haeena@haeena.net
Requires-Python: >=3.8,<4.0
Classifier: Development Status :: 3 - Alpha
Classifier: Intended Audience :: Developers
Classifier: License :: OSI Approved :: MIT License
Classifier: Programming Language :: Python :: 3
Classifier: Programming Language :: Python :: 3.8
Classifier: Typing :: Typed
Requires-Dist: starlette (>=0.13.0,<0.14.0)
Project-URL: Repository, https://github.com/haeena/slackevent-responder
